tox_conda/__init__.py
tox_conda/env_activator.py
tox_conda/plugin.py
tox_conda/version.py
tox_conda-0.10.2.dist-info/LICENSE
tox_conda-0.10.2.dist-info/METADATA
tox_conda-0.10.2.dist-info/WHEEL
tox_conda-0.10.2.dist-info/entry_points.txt
tox_conda-0.10.2.dist-info/top_level.txt
tox_conda-0.10.2.dist-info/RECORD
