Metadata-Version: 2.1
Name: tox-conda
Version: 0.10.2
Summary: tox plugin that provides integration with conda
Home-page: https://github.com/tox-dev/tox-conda
Author: Daniel R. D'Avella
Author-email: ddavella@stsci.edu
Maintainer: Bernat Gabor
Maintainer-email: gaborjbernat@gmail.com
License: MIT
Classifier: Development Status :: 4 - Beta
Classifier: Framework :: tox
Classifier: Intended Audience :: Developers
Classifier: License :: OSI Approved :: MIT License
Classifier: Operating System :: OS Independent
Classifier: Programming Language :: Python
Classifier: Programming Language :: Python :: 3
Classifier: Programming Language :: Python :: 3 :: Only
Classifier: Programming Language :: Python :: Implementation :: CPython
Classifier: Topic :: Software Development :: Testing
Requires-Python: >=3.5
License-File: LICENSE
Requires-Dist: ruamel.yaml (<0.18,>=0.15.0)
Requires-Dist: tox (<4,>=3.8.1)
